config_env/__init__.py
config_env-0.0.19.dist-info/LICENSE
config_env-0.0.19.dist-info/METADATA
config_env-0.0.19.dist-info/WHEEL
config_env-0.0.19.dist-info/top_level.txt
config_env-0.0.19.dist-info/RECORD
