Metadata-Version: 2.1
Name: config-env
Version: 0.0.19
Summary: Manage enviroment variables
Home-page: https://github.com/raslanribeiro/config_env
Author: Raslan Ribeiro
Author-email: raslan@poli.ufrj.br
License: UNKNOWN
Project-URL: Bug Tracker, https://github.com/raslanribeiro/config_env/issues
Platform: UNKNOWN
Classifier: Programming Language :: Python :: 3
Classifier: License :: OSI Approved :: MIT License
Classifier: Operating System :: OS Independent
Requires-Python: >=3.6
License-File: LICENSE
